jeeny_jeen/__init__.py
jeeny_jeen/main.py
jeeny_jeen-0.4.0.dist-info/METADATA
jeeny_jeen-0.4.0.dist-info/WHEEL
jeeny_jeen-0.4.0.dist-info/top_level.txt
jeeny_jeen-0.4.0.dist-info/RECORD
